kokorog2p/__init__.py
kokorog2p/_version.py
kokorog2p/abbreviation_utils.py
kokorog2p/attr_parser.py
kokorog2p/base.py
kokorog2p/espeak_g2p.py
kokorog2p/fallback_base.py
kokorog2p/goruut_g2p.py
kokorog2p/markers.py
kokorog2p/multilang.py
kokorog2p/phonemes.py
kokorog2p/pipeline_api.py
kokorog2p/punctuation.py
kokorog2p/py.typed
kokorog2p/span_processing.py
kokorog2p/token.py
kokorog2p/tokenization.py
kokorog2p/types.py
kokorog2p/vocab.py
kokorog2p/words_mismatch.py
kokorog2p/backends/__init__.py
kokorog2p/backends/espeak/__init__.py
kokorog2p/backends/espeak/api.py
kokorog2p/backends/espeak/backend.py
kokorog2p/backends/espeak/cli_wrapper.py
kokorog2p/backends/espeak/phonemizer_base.py
kokorog2p/backends/espeak/voice.py
kokorog2p/backends/espeak/wrapper.py
kokorog2p/backends/goruut/__init__.py
kokorog2p/backends/goruut/backend.py
kokorog2p/cs/__init__.py
kokorog2p/cs/abbreviations.py
kokorog2p/cs/fallback.py
kokorog2p/cs/g2p.py
kokorog2p/cs/normalizer.py
kokorog2p/cs/data/__init__.py
kokorog2p/data/__init__.py
kokorog2p/data/kokoro_config.json
kokorog2p/data/kokoro_config_v1.1_de.json
kokorog2p/data/kokoro_config_v1.1_zh.json
kokorog2p/de/__init__.py
kokorog2p/de/abbreviations.py
kokorog2p/de/fallback.py
kokorog2p/de/g2p.py
kokorog2p/de/lexicon.py
kokorog2p/de/normalizer.py
kokorog2p/de/numbers.py
kokorog2p/de/data/__init__.py
kokorog2p/de/data/de_gold.json
kokorog2p/en/__init__.py
kokorog2p/en/abbreviations.py
kokorog2p/en/fallback.py
kokorog2p/en/g2p.py
kokorog2p/en/lexicon.py
kokorog2p/en/normalizer.py
kokorog2p/en/numbers.py
kokorog2p/en/data/__init__.py
kokorog2p/en/data/gb_gold.json
kokorog2p/en/data/gb_silver.json
kokorog2p/en/data/us_gold.json
kokorog2p/en/data/us_silver.json
kokorog2p/es/__init__.py
kokorog2p/es/abbreviations.py
kokorog2p/es/g2p.py
kokorog2p/es/normalizer.py
kokorog2p/es/data/__init__.py
kokorog2p/fr/__init__.py
kokorog2p/fr/abbreviations.py
kokorog2p/fr/fallback.py
kokorog2p/fr/g2p.py
kokorog2p/fr/lexicon.py
kokorog2p/fr/normalizer.py
kokorog2p-0.6.5.dist-info/licenses/LICENSE
kokorog2p-0.6.5.dist-info/METADATA
kokorog2p-0.6.5.dist-info/WHEEL
kokorog2p-0.6.5.dist-info/top_level.txt
kokorog2p-0.6.5.dist-info/RECORD
