Metadata-Version: 2.4
Name: kokorog2p
Version: 0.6.5
Summary: A unified G2P (Grapheme-to-Phoneme) library for Kokoro TTS
Author-email: Holger Nahrstaedt <nahrstaedt@gmail.com>
License:                                  Apache License
Project-URL: Homepage, https://github.com/holgern/kokorog2p
Keywords: g2p,grapheme-to-phoneme,tts,text-to-speech,kokoro,phonemizer,espeak
Classifier: Development Status :: 4 - Beta
Classifier: Intended Audience :: Developers
Classifier: Intended Audience :: Science/Research
Classifier: License :: OSI Approved :: Apache Software License
Classifier: Operating System :: OS Independent
Classifier: Programming Language :: Python :: 3
Classifier: Programming Language :: Python :: 3.10
Classifier: Programming Language :: Python :: 3.11
Classifier: Programming Language :: Python :: 3.12
Classifier: Programming Language :: Python :: 3.13
Classifier: Topic :: Multimedia :: Sound/Audio :: Speech
Classifier: Topic :: Scientific/Engineering :: Artificial Intelligence
Classifier: Topic :: Software Development :: Libraries :: Python Modules
Classifier: Topic :: Text Processing :: Linguistic
Requires-Python: >=3.10
License-File: LICENSE
Provides-Extra: espeak
Requires-Dist: espeakng-loader>=0.1.0; extra == "espeak"
Requires-Dist: dlinfo>=1.2.1; extra == "espeak"
Provides-Extra: goruut
Requires-Dist: pygoruut>=0.7.0; extra == "goruut"
Provides-Extra: en
Requires-Dist: spacy>=3.5.0; extra == "en"
Requires-Dist: num2words>=0.5.12; extra == "en"
Provides-Extra: zh
Requires-Dist: jieba>=0.42.1; extra == "zh"
Requires-Dist: pypinyin>=0.49.0; extra == "zh"
Requires-Dist: cn2an>=0.5.22; extra == "zh"
Requires-Dist: pypinyin-dict>=0.8.0; extra == "zh"
Requires-Dist: ordered-set>=4.1.0; extra == "zh"
Provides-Extra: ja
Requires-Dist: pyopenjtalk>=0.3.0; extra == "ja"
Requires-Dist: fugashi>=1.3.0; extra == "ja"
Requires-Dist: jaconv>=0.3.4; extra == "ja"
Requires-Dist: mojimoji>=0.0.13; extra == "ja"
Requires-Dist: unidic>=1.1.0; extra == "ja"
Provides-Extra: ko
Requires-Dist: jamo>=0.4.1; extra == "ko"
Requires-Dist: nltk>=3.8.1; extra == "ko"
Provides-Extra: he
Requires-Dist: phonikud; extra == "he"
Provides-Extra: mixed
Requires-Dist: lingua-language-detector>=2.0.0; extra == "mixed"
Provides-Extra: all
Requires-Dist: kokorog2p[en,espeak,goruut,he,ja,ko,mixed,zh]; extra == "all"
Provides-Extra: dev
Requires-Dist: pytest>=7.0.0; extra == "dev"
Requires-Dist: pytest-cov>=4.0.0; extra == "dev"
Requires-Dist: ruff>=0.1.0; extra == "dev"
Requires-Dist: mypy>=1.0.0; extra == "dev"
Dynamic: license-file
